depex/__init__.py
depex/__main__.py
depex/cli.py
depex/extractor.py
depex-0.1.0.dist-info/LICENSE
depex-0.1.0.dist-info/METADATA
depex-0.1.0.dist-info/WHEEL
depex-0.1.0.dist-info/entry_points.txt
depex-0.1.0.dist-info/top_level.txt
depex-0.1.0.dist-info/RECORD
