Metadata-Version: 2.1
Name: depex
Version: 0.1.0
Summary: Extract project requirements from pyproject.toml.
Author-email: Josh Duncan <joshbduncan@gmail.com>
License: MIT License
Keywords: packaging,pyproject,toml,utility
Classifier: Intended Audience :: End Users/Desktop
Classifier: License :: OSI Approved :: MIT License
Classifier: Natural Language :: English
Classifier: Operating System :: OS Independent
Classifier: Programming Language :: Python
Classifier: Programming Language :: Python :: 3.10
Classifier: Programming Language :: Python :: 3.11
Classifier: Programming Language :: Python :: 3.12
Classifier: Typing :: Typed
Requires-Python: >=3.11
License-File: LICENSE
Provides-Extra: dev
Requires-Dist: black >=23.9.1 ; extra == 'dev'
Requires-Dist: flake8 >=6.1.0 ; extra == 'dev'
Requires-Dist: isort >=5.12.0 ; extra == 'dev'
Requires-Dist: mypy >=1.5.1 ; extra == 'dev'
Requires-Dist: pre-commit >=3.4.0 ; extra == 'dev'
Requires-Dist: pytest >=7.4.2 ; extra == 'dev'
Requires-Dist: pytest-cov >=4.1.0 ; extra == 'dev'
Requires-Dist: ruff >=0.0.292 ; extra == 'dev'
